{
  "folder": "Phat68gueYIk67lc",
  "name": "Greatsword",
  "type": "weapon",
  "img": "icons/svg/item-bag.svg",
  "system": {
    "description": "",
    "traits": {
      "raw": "[{\"key\":\"melee\",\"value\":\"Melee\",\"feature\":\"item\",\"subFeature\":\"identifiers\",\"effect\":\"\",\"data\":\"\",\"exclude\":[]},{\"key\":\"long\",\"value\":\"Long\",\"feature\":\"item\",\"subFeature\":\"identifiers\",\"effect\":\"\",\"data\":\"\",\"exclude\":[\"standard\",\"long\"]},{\"key\":\"weapon\",\"value\":\"Weapon\",\"feature\":\"item\",\"subFeature\":\"identifiers\",\"effect\":\"\",\"data\":\"\",\"exclude\":[]}]",
      "value": [
        {
          "key": "melee",
          "value": "Melee",
          "feature": "item",
          "subFeature": "identifiers",
          "effect": "",
          "data": "",
          "exclude": []
        },
        {
          "key": "long",
          "value": "Long",
          "feature": "item",
          "subFeature": "identifiers",
          "effect": "",
          "data": "",
          "exclude": [
            "standard",
            "long"
          ]
        }
      ]
    },
    "equipType": "held",
    "equipPoints": {
      "required": {
        "raw": "[]",
        "parsed": []
      },
      "provided": {
        "raw": "",
        "parsed": []
      }
    },
    "equipState": "stowed",
    "weapon": {
      "size": 8,
      "heft": 8
    },
    "attackProfiles": [
      {
        "name": "Slash",
        "attackType": "arc",
        "finisherLimit": 10,
        "hasStrongAttack": true,
        "critical": 10,
        "lethal": 0,
        "reach": "3",
        "damage": [
          {
            "type": "slashing",
            "value": 8,
            "penetration": 0,
            "attributeModifier": "str",
            "attributeMultiplier": 1,
            "damageMultiplier": 1,
            "overallMultiplier": 1
          }
        ],
        "range": 0,
        "penetration": 0,
        "ammunition": {
          "type": "",
          "id": "",
          "value": 0,
          "max": 0,
          "reloadType": "",
          "reloadActionCost": 1
        }
      },
      {
        "name": "Stab",
        "attackType": "thrust",
        "finisherLimit": 10,
        "hasStrongAttack": false,
        "critical": 10,
        "lethal": 0,
        "reach": "3",
        "damage": [
          {
            "type": "piercing",
            "value": 6,
            "penetration": 0,
            "attributeModifier": "str",
            "attributeMultiplier": 1,
            "damageMultiplier": 1,
            "overallMultiplier": 1
          }
        ],
        "range": 0,
        "penetration": 0,
        "ammunition": {
          "type": "",
          "id": "",
          "value": 0,
          "max": 0,
          "reloadType": "",
          "reloadActionCost": 1
        }
      }
    ],
    "handsRequired": "twoHand",
    "validEquipStates": [
      {
        "value": "held2H",
        "label": "ABBREW.EquipStateChange.heldTwo",
        "cost": 1
      },
      {
        "value": "dropped",
        "label": "ABBREW.EquipStateChange.dropped",
        "cost": 0
      }
    ],
    "abbrewId": {
      "value": "abbrew.weapon.greatsword.daBNLIlM2sYINFMv",
      "uuid": "daBNLIlM2sYINFMv"
    },
    "handsSupplied": 0,
    "actionCost": 0,
    "exertActionCost": 1,
    "isAttackTrained": false,
    "isFinisherTrained": false,
    "isFeintTrained": false,
    "isOverpowerTrained": false,
    "meta": {
      "quality": 0,
      "tier": 0
    },
    "name": {
      "parts": [],
      "base": "Greatsword"
    },
    "enhancements": [],
    "availableEnhancements": 0,
    "heft": 10
  },
  "effects": [],
  "ownership": {
    "default": 0
  },
  "flags": {},
  "_stats": {
    "duplicateSource": null,
    "coreVersion": "12.331",
    "systemId": "abbrew",
    "systemVersion": "0.0.2-prerelease31",
    "createdTime": 1743075324307,
    "modifiedTime": 1748899090289,
    "lastModifiedBy": "abbrewpacks00000"
  },
  "_id": "daBNLIlM2sYINFMv",
  "sort": 200000,
  "_key": "!items!daBNLIlM2sYINFMv"
}
